tablerone/__init__.py
tablerone/py.typed
tablerone-0.1.0.dist-info/METADATA
tablerone-0.1.0.dist-info/WHEEL
tablerone-0.1.0.dist-info/licenses/LICENSE
tablerone-0.1.0.dist-info/RECORD
