Metadata-Version: 2.3
Name: tablerone
Version: 0.1.0
Summary: A highly customizable package to create terminal tables from 2D sequences.
Author-email: machadinhos <pbmachado2002@gmail.com>
License: MIT License
License-File: LICENSE
Keywords: ascii,format,pretty,print,table,terminal,unicode
Classifier: Development Status :: 3 - Alpha
Classifier: Intended Audience :: Developers
Classifier: License :: OSI Approved :: MIT License
Classifier: Operating System :: OS Independent
Classifier: Programming Language :: Python :: 3
Classifier: Programming Language :: Python :: 3 :: Only
Classifier: Programming Language :: Python :: 3.8
Classifier: Programming Language :: Python :: 3.9
Classifier: Programming Language :: Python :: 3.10
Classifier: Programming Language :: Python :: 3.11
Classifier: Topic :: Software Development :: Libraries
Classifier: Topic :: Software Development :: Libraries :: Python Modules
Classifier: Topic :: Utilities
Classifier: Typing :: Typed
Requires-Python: >=3.12
